.long-description.html
MANIFEST.in
README.rst
setup.py
Products/__init__.py
Products.EventRegistration.egg-info/PKG-INFO
Products.EventRegistration.egg-info/SOURCES.txt
Products.EventRegistration.egg-info/dependency_links.txt
Products.EventRegistration.egg-info/entry_points.txt
Products.EventRegistration.egg-info/namespace_packages.txt
Products.EventRegistration.egg-info/not-zip-safe
Products.EventRegistration.egg-info/requires.txt
Products.EventRegistration.egg-info/top_level.txt
Products/EventRegistration/CREDITS.txt
Products/EventRegistration/LICENSE.txt
Products/EventRegistration/README.txt
Products/EventRegistration/__init__.py
Products/EventRegistration/config.py
Products/EventRegistration/configure.zcml
Products/EventRegistration/events.py
Products/EventRegistration/registerable_event.py
Products/EventRegistration/registrant.py
Products/EventRegistration/utils.py
Products/EventRegistration/version.txt
Products/EventRegistration/profiles/default/propertiestool.xml
Products/EventRegistration/profiles/default/skins.xml
Products/EventRegistration/profiles/default/types.xml
Products/EventRegistration/profiles/default/workflows.xml
Products/EventRegistration/profiles/default/types/RegisterableEvent.xml
Products/EventRegistration/profiles/default/types/Registrant.xml
Products/EventRegistration/profiles/default/workflows/event_workflow/definition.xml
Products/EventRegistration/profiles/default/workflows/registrant_workflow/definition.xml
Products/EventRegistration/skins/event_registration/allRegEmail.py
Products/EventRegistration/skins/event_registration/export_registrants.pt
Products/EventRegistration/skins/event_registration/export_registrants.pt.metadata
Products/EventRegistration/skins/event_registration/mail_registrants.cpt
Products/EventRegistration/skins/event_registration/mail_registrants.cpt.metadata
Products/EventRegistration/skins/event_registration/registerable_event_view.pt
Products/EventRegistration/skins/event_registration/registrant_edit.pt
Products/EventRegistration/skins/event_registration/registrant_view.pt
Products/EventRegistration/skins/event_registration/saveHook.cpy
Products/EventRegistration/skins/event_registration/saveHook.cpy.metadata
Products/EventRegistration/skins/event_registration/send_feedback.dtml
Products/EventRegistration/skins/event_registration/validate_integrity.cpy
