Metadata-Version: 1.1
Name: Products.EventRegistration
Version: 1.0.4
Summary: An event registration system for plone
Home-page: https://github.com/collective/Products.EventRegistration
Author: Alex Clark
Author-email: aclark@aclark.net
License: GPL
Keywords: plone events
Platform: UNKNOWN
Classifier: Framework :: Plone
Classifier: Programming Language :: Python
Classifier: Topic :: Software Development :: Libraries :: Python Modules
